{"name":"Yam","tagline":"a user interface system for game","body":"# Yam\r\n\r\nA UI System\r\n\r\n\r\n## Projects\r\n\r\n* Yam's library\r\n* Photoshop Plug-In\r\n* Yam's editor by Qt\r\n\r\n\r\n### Yam's library\r\n\r\n> The core of yam, is a static library, was linked by other project.\r\n\r\nIt will include the basic element of UI system, likes widget, panel, layout and layer.\r\n\r\n\r\n### Photoshop Plug-In\r\n\r\n> The plugin of Adobe Photoshop, is the file format module, can save the yam to file.\r\n\r\nWe need use Adobe Photoshop to save the layer and image to yam format.\r\n\r\n\r\n### Yam's editor by Qt\r\n\r\n> A executable file, to edit/save the yam file.\r\n\r\nYou can use it to edit/save the yam file and export the new format file.\r\n\r\n\r\n## Getting Started\r\n\r\n### Requirement\r\n\r\n* CMake\r\n* Visual Studio 2012 Express\r\n* Qt\r\n\r\n### Environment\r\n\r\n* set the PS\\_PLUGIN\\_SDK to the SDK directory for Photoshop Plug-In\r\n* set the QT\\_MSVC2012\\_X32 to the Qt directory for VC2012 x32\r\n* set the QT\\_MSVC2012\\_X64 to the Qt directory for VC2012 x64\r\n\r\n### License\r\n\r\nSee The MIT License or LICENSE file","google":"UA-37594072-1","note":"Don't delete this file! It's used internally to help with page regeneration."}